startnet/__init__.py
startnet/__main__.py
startnet/version.py
startnet/config/__init__.py
startnet/config/app.py
startnet/config/logging.py
startnet/controller/__init__.py
startnet/controller/controller.py
startnet/data/oem-codes.csv
startnet/packets/__init__.py
startnet/packets/art_address.py
startnet/packets/art_command.py
startnet/packets/art_diag_data.py
startnet/packets/art_dmx.py
startnet/packets/art_input.py
startnet/packets/art_ip_prog.py
startnet/packets/art_ip_prog_reply.py
startnet/packets/art_nzs.py
startnet/packets/art_poll.py
startnet/packets/art_poll_reply.py
startnet/packets/art_sync.py
startnet/packets/art_time_code.py
startnet/packets/art_trigger.py
startnet/packets/art_vlc.py
startnet/packets/base.py
startnet/protocol/__init__.py
startnet/protocol/constants.py
startnet/protocol/diag_priority_codes.py
startnet/protocol/op_codes.py
startnet/utils/__init__.py
startnet/utils/common_args.py
startnet/utils/grid.py
startnet/utils/network.py
startnet-0.1.0.dist-info/LICENSE
startnet-0.1.0.dist-info/METADATA
startnet-0.1.0.dist-info/WHEEL
startnet-0.1.0.dist-info/entry_points.txt
startnet-0.1.0.dist-info/top_level.txt
startnet-0.1.0.dist-info/RECORD
