Metadata-Version: 2.1
Name: startnet
Version: 0.1.0
Summary: startnet - Art-Net protocol implementation
Home-page: https://github.com/sunarch/startnet
Author: András Németh (sunarch)
Author-email: sunarch@protonmail.com
Maintainer: András Németh (sunarch)
Maintainer-email: sunarch@protonmail.com
License: Mozilla Public License 2.0 (MPL 2.0)
Project-URL: Bug Tracker, https://github.com/sunarch/startnet/issues
Keywords: startnet,Art-Net
Platform: Any
Classifier: Programming Language :: Python :: 3
Classifier: License :: OSI Approved :: Mozilla Public License 2.0 (MPL 2.0)
Classifier: Operating System :: OS Independent
Classifier: Environment :: Console
Classifier: Environment :: Web Environment
Classifier: Development Status :: 2 - Pre-Alpha
Classifier: Intended Audience :: End Users/Desktop
Classifier: Intended Audience :: Developers
Classifier: Topic :: Artistic Software
Classifier: Topic :: Multimedia
Classifier: Topic :: System :: Networking
Classifier: Typing :: Typed
Requires-Python: >=3.9
License-File: LICENSE
Requires-Dist: webcolors (~=1.12)
Requires-Dist: xdg-base-dirs (==6.0.0)
